[
    {
        "accuracy": 0.45794683143985176,
        "macro_f1": 0.49609791307973194,
        "macro_precision": 0.48852524903593525,
        "macro_recall": 0.534649202931692,
        "micro_f1": 0.5855558885226251,
        "micro_precision": 0.559351145038168,
        "micro_recall": 0.6143366170614127,
        "official_calculation": {
            "Achievement": 0.59,
            "Face": 0.3,
            "Hedonism": 0.19,
            "Humility": 0.15,
            "Stimulation": 0.19,
            "Tradition": 0.57,
            "action": 0.7,
            "avg-f1-score": 0.5,
            "caring": 0.58,
            "concern": 0.75,
            "dependability": 0.4,
            "dominance": 0.47,
            "interpersonal": 0.31,
            "nature": 0.82,
            "objectivity": 0.49,
            "personal": 0.75,
            "resources": 0.52,
            "rules": 0.54,
            "societal": 0.63,
            "thought": 0.59,
            "tolerance": 0.39
        }
    }
]